{
  "estado": 0,
  "aberto": true,
  "soma": -10,
  "altistas": 2,
  "neutros": 5,
  "baixistas": 12,
  "total": 19,
  "fechados": 6,
  "lista_altistas": [
    "TOPIX Futuros",
    "China H-Shares Futuros"
  ],
  "lista_neutros": [
    "DAX Futuros",
    "Petróleo Brent",
    "Ouro",
    "Petróleo WTI",
    "DXY (dolar)"
  ],
  "lista_baixistas": [
    "Euro Stoxx 50 Futuros",
    "KOSPI 200 Futuros",
    "Hang Seng Futuros",
    "S&P 500 VIX Futuros",
    "IBEX 35 Futuros",
    "Topix 100",
    "S&P/ASX 200 Futuros",
    "Nasdaq 100 Futuros",
    "S&P 500 Futuros",
    "Dow Jones Futuros",
    "Nikkei 225 Futuros",
    "Prata"
  ],
  "atualizado": "2026-07-17T06:03:06.073Z",
  "obs": "So ativos abertos (relogio verde). Fechados ignorados: 6. Veredito por maioria. Carteira do Investing + DXY do TradingView (WINPRIME)."
}