{
  "estado": 1,
  "aberto": true,
  "soma": 1,
  "altistas": 4,
  "neutros": 10,
  "baixistas": 3,
  "total": 17,
  "fechados": 8,
  "lista_altistas": [
    "KOSPI 200 Futuros",
    "Nikkei 225 Futuros",
    "Topix 100",
    "Hang Seng Futuros"
  ],
  "lista_neutros": [
    "Petróleo Brent",
    "S&P/ASX 200 Futuros",
    "DAX Futuros",
    "Ouro",
    "Dow Jones Futuros",
    "Petróleo WTI",
    "Prata",
    "S&P 500 Futuros",
    "China H-Shares Futuros",
    "DXY (dolar)"
  ],
  "lista_baixistas": [
    "S&P 500 VIX Futuros",
    "Nasdaq 100 Futuros",
    "TOPIX Futuros"
  ],
  "atualizado": "2026-07-10T01:15:59.728Z",
  "obs": "So ativos abertos (relogio verde). Fechados ignorados: 8. Carteira do Investing + DXY do TradingView (WINPRIME)."
}