{
  "estado": 2,
  "aberto": true,
  "soma": 5,
  "altistas": 5,
  "neutros": 6,
  "baixistas": 0,
  "total": 11,
  "fechados": 13,
  "lista_altistas": [
    "Petróleo Brent",
    "Petróleo WTI",
    "Prata",
    "Ouro",
    "S&P/ASX 200 Futuros"
  ],
  "lista_neutros": [
    "S&P 500 VIX Futuros",
    "Dow Jones Futuros",
    "S&P 500 Futuros",
    "DAX Futuros",
    "Nasdaq 100 Futuros",
    "DXY (dolar)"
  ],
  "lista_baixistas": [],
  "atualizado": "2026-07-22T20:28:13.149Z",
  "obs": "So ativos abertos (relogio verde). Fechados ignorados: 13. Veredito por maioria. Carteira do Investing + DXY do TradingView (WINPRIME)."
}