{
  "estado": 2,
  "aberto": true,
  "soma": 2,
  "altistas": 3,
  "neutros": 5,
  "baixistas": 1,
  "total": 9,
  "fechados": 16,
  "lista_altistas": [
    "Nasdaq 100 Futuros",
    "S&P 500 Futuros",
    "Morgan Stanley"
  ],
  "lista_neutros": [
    "iShares MSCI Brazil Capped",
    "Dow Jones Futuros",
    "Mini Ibovespa Futuros",
    "Ibovespa",
    "DXY (dolar)"
  ],
  "lista_baixistas": [
    "Mini S&P 500 VIX Futuros"
  ],
  "atualizado": "2026-07-20T13:31:17.978Z",
  "obs": "So ativos abertos (relogio verde). Fechados ignorados: 16. Veredito por maioria. Carteira do Investing + DXY do TradingView (WINPRIME)."
}